RedisBridge/__init__.py
RedisBridge/bridge.py
RedisBridge/utils.py
RedisBridge/interfaces/__init__.py
RedisBridge/interfaces/base.py
RedisBridge/interfaces/callback.py
RedisBridge/messages/__init__.py
RedisBridge/messages/base.py
RedisBridge/messages/request_response.py
RedisBridge-2.0.4.dist-info/LICENSE.txt
RedisBridge-2.0.4.dist-info/METADATA
RedisBridge-2.0.4.dist-info/WHEEL
RedisBridge-2.0.4.dist-info/top_level.txt
RedisBridge-2.0.4.dist-info/RECORD
