Metadata-Version: 2.1
Name: RedisBridge
Version: 2.0.4
Summary: Send and receive messages via a Redis server
Home-page: https://github.com/ini/RedisBridge
Author: Ini Oguntola
Author-email: ini@alum.mit.edu
Classifier: Programming Language :: Python :: 3
Classifier: License :: OSI Approved :: MIT License
Classifier: Operating System :: OS Independent
Requires-Python: >=3.6
License-File: LICENSE.txt
Requires-Dist: redis (>=3)
Requires-Dist: fakeredis
